{
  "capture_timestamp": "2025-01-31T17:20:00Z",
  "capture_method": "HTTP endpoint testing and file system analysis",
  "render_deployment_status": {
    "web_service": {
      "expected_url": "https://worldchef-staging.onrender.com",
      "status": "NOT_DEPLOYED",
      "evidence": "SSL/TLS connection failure, timeout on health endpoint"
    },
    "api_service": {
      "expected_url": "https://api.worldchef-staging.onrender.com", 
      "status": "NOT_DEPLOYED",
      "evidence": "SSL/TLS secure channel error"
    }
  },
  "application_files_status": {
    "app.js": {
      "exists": false,
      "expected_location": "./app.js",
      "documented_in_week0": true,
      "reality_gap": "CRITICAL - Application file missing"
    },
    "package.json": {
      "exists": true,
      "location": "./package.json",
      "notes": "Root package.json exists but may not contain application code"
    }
  },
  "comparison_to_week0_docs": {
    "minimal_app_deployment_guide": {
      "guide_location": "docs/cycle4/week0/minimal_app_deployment_guide.md",
      "deployment_expectation": "Deploy app.js + package.json to Render",
      "reality": "NO_APP_FILES_TO_DEPLOY",
      "gap": "Application files don't exist"
    }
  },
  "validation_notes": [
    "Week 0 staging_current_state.md correctly identified: 'No actual web services running on Render'",
    "Missing app.js file confirms deployment hasn't occurred",
    "Health endpoint testing confirms no services are live",
    "Infrastructure Reality Capture validates Week 0 gap analysis"
  ]
} 